peext-0.5.2-py3.8-nspkg.pth
peext/controller.py
peext/core.py
peext/edge.py
peext/network.py
peext/node.py
peext/storage.py
peext/data/__init__.py
peext/data/core.py
peext/data/plotting.py
peext/scenario/__init__.py
peext/scenario/example_dh_uk.py
peext/scenario/network.py
peext/world/__init__.py
peext/world/core.py
peext-0.5.2.dist-info/METADATA
peext-0.5.2.dist-info/WHEEL
peext-0.5.2.dist-info/namespace_packages.txt
peext-0.5.2.dist-info/top_level.txt
peext-0.5.2.dist-info/RECORD
