Metadata-Version: 2.1
Name: peext
Version: 0.5.2
Summary: pandaenergy-extension
Author: Rico Schrage
Author-email: rico.schrage@uni-oldenburg.de
License: MIT
Platform: UNKNOWN
Classifier: License :: OSI Approved :: MIT License
Classifier: Programming Language :: Python
Classifier: Programming Language :: Python :: 3
Classifier: Programming Language :: Python :: 3.7
Classifier: Programming Language :: Python :: Implementation :: CPython
Classifier: Programming Language :: Python :: Implementation :: PyPy
Requires-Python: >=3.7.0
Requires-Dist: pandapipes
Requires-Dist: pandapower
Requires-Dist: numpy
Requires-Dist: overrides
Requires-Dist: pandas
Requires-Dist: mango-agents (==0.3.0)
Requires-Dist: simbench
